Metadata-Version: 2.4
Name: aec-audio-processing-fork
Version: 1.0.1.dev1
Summary: AEC(Acoustic Echo Cancellation) Audio Processing Module
Author-email: TheDeveloper <yourappleintelligence@gmail.com>
License-Expression: BSD-3-Clause
Keywords: acoustic echo cancellation,webrtc audioprocessing,voice activity detection,noise suppression,automatic gain control
Classifier: Development Status :: 5 - Production/Stable
Classifier: Intended Audience :: Developers
Classifier: Operating System :: POSIX :: Linux
Classifier: Operating System :: MacOS :: MacOS X
Classifier: Programming Language :: Python :: 3
Classifier: Programming Language :: C++
Classifier: Topic :: Multimedia :: Sound/Audio :: Analysis
Classifier: Topic :: Multimedia :: Sound/Audio :: Speech
Requires-Python: >=3.11
License-File: LICENSE
Dynamic: license-file
